setup.py
bgp_visualize/__init__.py
bgp_visualize/bgp_visualize_asn.py
bgp_visualize/test1.py
bgp_visualize.egg-info/PKG-INFO
bgp_visualize.egg-info/SOURCES.txt
bgp_visualize.egg-info/dependency_links.txt
bgp_visualize.egg-info/requires.txt
bgp_visualize.egg-info/top_level.txt